scrape/__init__.py
scrape/crawler.py
scrape/orderedset.py
scrape/scrape.py
scrape/utils.py
scrape-0.11.3.dist-info/LICENSE.txt
scrape-0.11.3.dist-info/METADATA
scrape-0.11.3.dist-info/WHEEL
scrape-0.11.3.dist-info/entry_points.txt
scrape-0.11.3.dist-info/top_level.txt
scrape-0.11.3.dist-info/RECORD
