Metadata-Version: 2.1
Name: scrape
Version: 0.11.3
Summary: a command-line web scraping tool
Home-page: https://github.com/huntrar/scrape
Author: Hunter H
Author-email: huntrar@gmail.com
Maintainer: Hunter H
Maintainer-email: huntrar@gmail.com
License: MIT
Keywords: web crawler scraper scrape crawl download filter save webpages websites images docs document documentation pdf csv html lxml
Platform: UNKNOWN
Classifier: Development Status :: 4 - Beta
Classifier: Environment :: Console
Classifier: Environment :: Web Environment
Classifier: Intended Audience :: End Users/Desktop
Classifier: Intended Audience :: Developers
Classifier: Intended Audience :: System Administrators
Classifier: License :: OSI Approved :: MIT License
Classifier: Operating System :: OS Independent
Classifier: Programming Language :: Python :: 3
Classifier: Programming Language :: Python :: 3.6
Classifier: Programming Language :: Python :: 3.7
Classifier: Programming Language :: Python :: 3.8
Classifier: Programming Language :: Python :: 3.9
Classifier: Topic :: Utilities
Classifier: Topic :: Text Processing
License-File: LICENSE.txt
